{"slug":"find-digital-root-of-a-number","title":"Find Digital Root of a number","trackId":3060,"tags":["C","Java","JavaScript","Ruby","TypeScript","Python","GO"],"contributors":["joao-vitor-souza","lukastomcisak","devkansara","omprakashchhetri","Akhilbisht798","Greeshma-frontier","Vishwamagdavan","harshraj8843"],"contentHtml":"<h2>Write a program to find digital root of a number</h2>\n<p>Digital root of a number is the recursive sum of its digits until we get a single digit number.</p>\n<pre><code>Input  : 1234\r\nOutput : 1\n</code></pre>\n<hr>\n<pre><code>404: Not Found\n</code></pre>\n<pre><code>404: Not Found\n</code></pre>\n<pre><code>404: Not Found\n</code></pre>\n<pre><code>404: Not Found\n</code></pre>\n<pre><code>404: Not Found\n</code></pre>\n<pre><code>404: Not Found\n</code></pre>\n<pre><code>404: Not Found\n</code></pre>\n","markdown":"\n## Write a program to find digital root of a number\n\nDigital root of a number is the recursive sum of its digits until we get a single digit number.\r\n\r\n```\r\nInput  : 1234\r\nOutput : 1\r\n```\n\n---\n\n<CodeBlock>\n\n```c\n404: Not Found\n```\n\n```java\n404: Not Found\n```\n\n```js\n404: Not Found\n```\n\n```rb\n404: Not Found\n```\n\n```ts\n404: Not Found\n```\n\n```py\n404: Not Found\n```\n\n```go\n404: Not Found\n```\n\n</CodeBlock>\n\n","latestUpdateDate":"2022-12-02T06:03:31Z"}