{"slug":"find-area-of-a-right-angled-triangle","title":"Find area of a right angled triangle","trackId":756,"tags":["C","C++","Java","JavaScript","TypeScript","Python","GO","PHP"],"contributors":["joao-vitor-souza","harshraj8843","PoweredByCaffein","rajdip-b","MadhuS-1605","anastazir","christiankilpatrick-dev","SRR-CODER","marcobuontempo"],"contentHtml":"<h2>Write a program to find area of a right angled triangle</h2>\n<p>Area of right angled triangle = 0.5 × <code>Base</code> × <code>Height</code></p>\n<pre><code>Base   : 2\r\nHeight : 3\r\n\r\nArea : 3\n</code></pre>\n<hr>\n<pre><code>404: Not Found\n</code></pre>\n<pre><code>404: Not Found\n</code></pre>\n<pre><code>404: Not Found\n</code></pre>\n<pre><code>404: Not Found\n</code></pre>\n<pre><code>404: Not Found\n</code></pre>\n<pre><code>404: Not Found\n</code></pre>\n<pre><code>404: Not Found\n</code></pre>\n<pre><code>404: Not Found\n</code></pre>\n","markdown":"\n## Write a program to find area of a right angled triangle\n\nArea of right angled triangle = 0.5 × `Base` × `Height`\r\n\r\n```\r\nBase   : 2\r\nHeight : 3\r\n\r\nArea : 3\r\n```\n\n---\n\n<CodeBlock>\n\n```c\n404: Not Found\n```\n\n```cpp\n404: Not Found\n```\n\n```java\n404: Not Found\n```\n\n```js\n404: Not Found\n```\n\n```ts\n404: Not Found\n```\n\n```py\n404: Not Found\n```\n\n```go\n404: Not Found\n```\n\n```php\n404: Not Found\n```\n\n</CodeBlock>\n\n","latestUpdateDate":"2022-12-02T06:03:31Z"}